RoundBox/__init__.py
RoundBox/__main__.py
RoundBox/apps/__init__.py
RoundBox/apps/config.py
RoundBox/apps/config.pyi
RoundBox/apps/license.txt
RoundBox/apps/registry.py
RoundBox/apps/registry.pyi
RoundBox/conf/__init__.py
RoundBox/conf/app_settings.py
RoundBox/conf/global_settings.py
RoundBox/conf/jobs_template/jobs/__init__.py.tmpl
RoundBox/conf/jobs_template/jobs/daily/__init__.py.tmpl
RoundBox/conf/jobs_template/jobs/hourly/__init__.py.tmpl
RoundBox/conf/jobs_template/jobs/minutely/__init__.py.tmpl
RoundBox/conf/jobs_template/jobs/monthly/__init__.py.tmpl
RoundBox/conf/jobs_template/jobs/quarter_hourly/__init__.py.tmpl
RoundBox/conf/jobs_template/jobs/sample.py.tmpl
RoundBox/conf/jobs_template/jobs/weekly/__init__.py.tmpl
RoundBox/conf/jobs_template/jobs/yearly/__init__.py.tmpl
RoundBox/conf/license.txt
RoundBox/conf/project_settings.py
RoundBox/const.py
RoundBox/core/__init__.py
RoundBox/core/cache/__init__.py
RoundBox/core/cache/backends/__init__.py
RoundBox/core/cache/backends/base.py
RoundBox/core/cache/backends/dummy.py
RoundBox/core/cache/backends/filebased.py
RoundBox/core/cache/backends/locmem.py
RoundBox/core/checks/__init__.py
RoundBox/core/checks/dependency.py
RoundBox/core/checks/files.py
RoundBox/core/checks/messages.py
RoundBox/core/checks/registry.py
RoundBox/core/cliparser/__init__.py
RoundBox/core/cliparser/base.py
RoundBox/core/cliparser/color.py
RoundBox/core/cliparser/commands/__init__.py
RoundBox/core/cliparser/commands/check.py
RoundBox/core/cliparser/commands/clean_pyc.py
RoundBox/core/cliparser/commands/compile_pyc.py
RoundBox/core/cliparser/commands/create_jobs.py
RoundBox/core/cliparser/commands/notes.py
RoundBox/core/cliparser/commands/pipchecker.py
RoundBox/core/cliparser/commands/print_settings.py
RoundBox/core/cliparser/commands/runjob.py
RoundBox/core/cliparser/commands/runjobs.py
RoundBox/core/cliparser/commands/runserver.py
RoundBox/core/cliparser/jobs.py
RoundBox/core/cliparser/signals.py
RoundBox/core/cliparser/utils.py
roundbox-1.0.dist-info/entry_points.txt
roundbox-1.0.dist-info/LICENSE
roundbox-1.0.dist-info/WHEEL
roundbox-1.0.dist-info/METADATA
roundbox-1.0.dist-info/RECORD
