Metadata-Version: 2.1
Name: roundbox
Version: 1.0
Summary: A small lightweight framework for IoT applications
Home-page: https://github.com/soulraven/roundbox
License: LICENSE.md
Keywords: roundbox,template,poetry
Author: Zaharia Constantin
Author-email: layout.webdesign@gmail.com
Requires-Python: >=3.10,<4.0
Classifier: Intended Audience :: Developers
Classifier: License :: OSI Approved :: GNU General Public License v3 or later (GPLv3+)
Classifier: License :: Other/Proprietary License
Classifier: Operating System :: OS Independent
Classifier: Programming Language :: Python
Classifier: Programming Language :: Python :: 3
Classifier: Programming Language :: Python :: 3.10
Classifier: Programming Language :: Python :: 3.11
Classifier: Topic :: Home Automation
Classifier: Topic :: Software Development :: Libraries
Classifier: Topic :: Software Development :: Libraries :: Python Modules
Provides-Extra: lint
Provides-Extra: mkdocs
Provides-Extra: test
Requires-Dist: colorama
Requires-Dist: slugify (>=0.0.1,<0.0.2)
Requires-Dist: watchdog
Project-URL: Documentation, https://soulraven.github.io/roundbox/
Project-URL: Discussions, https://github.com/soulraven/roundbox/discussions
Project-URL: Issues, https://github.com/soulraven/roundbox/issues
Project-URL: Repository, https://github.com/soulraven/roundbox
Project-URL: Releases, https://soulraven.github.io/roundbox/releases
Project-URL: Source, https://github.com/soulraven/roundbox
